Youtube/__init__.py
Youtube/activities.py
Youtube/api_mapper.py
Youtube/captions.py
Youtube/channel.py
Youtube/class_mapper.py
Youtube/client.py
Youtube/comments.py
Youtube/parser.py
Youtube/playlist.py
Youtube/search.py
Youtube/video.py
pytubedata-1.1.0.dist-info/LICENSE
pytubedata-1.1.0.dist-info/METADATA
pytubedata-1.1.0.dist-info/WHEEL
pytubedata-1.1.0.dist-info/top_level.txt
pytubedata-1.1.0.dist-info/RECORD
