Metadata-Version: 2.1
Name: pytubedata
Version: 1.1.0
Summary: A simple wrapper for YouTube Data API v3 written in Python
Home-page: https://github.com/professor91/pytubedata
Author: Keshav Saini
Author-email: keshavandteam@gmail.com
License: MIT
Keywords: youtubedata,youtubedataapi,pytubedata,pytubedata.py,googleapi
Platform: UNKNOWN
Classifier: License :: OSI Approved :: MIT License
Classifier: Programming Language :: Python :: 3
Classifier: Programming Language :: Python :: 3.7
Classifier: Operating System :: OS Independent
License-File: LICENSE
Requires-Dist: requests
